dadbscan/__init__.py
dadbscan/clustering.py
dadbscan/density.py
dadbscan-0.3.dist-info/LICENSE
dadbscan-0.3.dist-info/METADATA
dadbscan-0.3.dist-info/WHEEL
dadbscan-0.3.dist-info/top_level.txt
dadbscan-0.3.dist-info/RECORD
